st_clickable_img_gallery/__init__.py
st_clickable_img_gallery/frontend/build/asset-manifest.json
st_clickable_img_gallery/frontend/build/bootstrap.min.css
st_clickable_img_gallery/frontend/build/index.html
st_clickable_img_gallery/frontend/build/precache-manifest.e559788480d29b4d2c2155e0fa12e735.js
st_clickable_img_gallery/frontend/build/service-worker.js
st_clickable_img_gallery/frontend/build/static/js/2.60f28383.chunk.js
st_clickable_img_gallery/frontend/build/static/js/2.60f28383.chunk.js.LICENSE.txt
st_clickable_img_gallery/frontend/build/static/js/2.60f28383.chunk.js.map
st_clickable_img_gallery/frontend/build/static/js/main.8598a375.chunk.js
st_clickable_img_gallery/frontend/build/static/js/main.8598a375.chunk.js.map
st_clickable_img_gallery/frontend/build/static/js/runtime-main.11ec9aca.js
st_clickable_img_gallery/frontend/build/static/js/runtime-main.11ec9aca.js.map
st_clickable_img_gallery-0.0.7.dist-info/LICENSE
st_clickable_img_gallery-0.0.7.dist-info/METADATA
st_clickable_img_gallery-0.0.7.dist-info/WHEEL
st_clickable_img_gallery-0.0.7.dist-info/top_level.txt
st_clickable_img_gallery-0.0.7.dist-info/RECORD
