Metadata-Version: 2.1
Name: st-clickable-img-gallery
Version: 0.0.7
Summary: A Streamlit component to display clickable images
Home-page: 
Author: 
Author-email: 
Requires-Python: >=3.6
License-File: LICENSE
Requires-Dist: streamlit (>=0.63)
